uipath_connectors/uipath_airdk/__init__.py
uipath_connectors/uipath_airdk/client.py
uipath_connectors/uipath_airdk/errors.py
uipath_connectors/uipath_airdk/py.typed
uipath_connectors/uipath_airdk/types.py
uipath_connectors/uipath_airdk/api/__init__.py
uipath_connectors/uipath_airdk/api/categorize/__init__.py
uipath_connectors/uipath_airdk/api/categorize/categorize.py
uipath_connectors/uipath_airdk/api/classification/__init__.py
uipath_connectors/uipath_airdk/api/classification/image_classification.py
uipath_connectors/uipath_airdk/api/ecssearch/__init__.py
uipath_connectors/uipath_airdk/api/ecssearch/context_grounding_search.py
uipath_connectors/uipath_airdk/api/generate_email/__init__.py
uipath_connectors/uipath_airdk/api/generate_email/generate_email.py
uipath_connectors/uipath_airdk/api/image_comparison/__init__.py
uipath_connectors/uipath_airdk/api/image_comparison/image_comparison.py
uipath_connectors/uipath_airdk/api/language_detection/__init__.py
uipath_connectors/uipath_airdk/api/language_detection/language_detection.py
uipath_connectors/uipath_airdk/api/ner/__init__.py
uipath_connectors/uipath_airdk/api/ner/named_entity_recognition.py
uipath_connectors/uipath_airdk/api/pii_detection/__init__.py
uipath_connectors/uipath_airdk/api/pii_detection/pii_detection.py
uipath_connectors/uipath_airdk/api/rewrite/__init__.py
uipath_connectors/uipath_airdk/api/rewrite/rewrite.py
uipath_connectors/uipath_airdk/api/semantic_similarity/__init__.py
uipath_connectors/uipath_airdk/api/semantic_similarity/semantic_similarity.py
uipath_connectors/uipath_airdk/api/signature_similarity/__init__.py
uipath_connectors/uipath_airdk/api/signature_similarity/signature_similarity.py
uipath_connectors/uipath_airdk/api/summarise/__init__.py
uipath_connectors/uipath_airdk/api/summarise/summarise_text_new.py
uipath_connectors/uipath_airdk/api/translate/__init__.py
uipath_connectors/uipath_airdk/api/translate/translate.py
uipath_connectors/uipath_airdk/api/update_index/__init__.py
uipath_connectors_uipath_airdk-1.53.11.dev12.dist-info/METADATA
uipath_connectors_uipath_airdk-1.53.11.dev12.dist-info/WHEEL
uipath_connectors_uipath_airdk-1.53.11.dev12.dist-info/entry_points.txt
uipath_connectors_uipath_airdk-1.53.11.dev12.dist-info/top_level.txt
uipath_connectors_uipath_airdk-1.53.11.dev12.dist-info/RECORD
